scikit_stan-0.1.1.dist-info/top_level.txt
scikit_stan-0.1.1.dist-info/WHEEL
scikit_stan-0.1.1.dist-info/METADATA
scikit_stan-0.1.1.dist-info/RECORD
scikit_stan-0.1.1.dist-info/LICENSE
scikit_stan/_version.py
scikit_stan/py.typed
scikit_stan/exceptions.py
scikit_stan/__init__.py
scikit_stan/modelcore.py
scikit_stan/stan_files/glm_v_discrete.stan
scikit_stan/stan_files/glm_v_continuous.exe
scikit_stan/stan_files/glm_v_continuous.stan
scikit_stan/stan_files/glm_v_discrete.exe
scikit_stan/stan_files/__init__.py
scikit_stan/stan_files/common/glm_priors.stan
scikit_stan/stan_files/common/make_mu.stan
scikit_stan/stan_files/common/functions.stan
scikit_stan/stan_files/common/glm_data.stan
scikit_stan/stan_files/common/__init__.py
scikit_stan/stan_files/likelihoods/discrete.stan
scikit_stan/stan_files/likelihoods/continuous.stan
scikit_stan/stan_files/likelihoods/__init__.py
scikit_stan/stan_files/cmdstan-2.30.1/makefile
scikit_stan/stan_files/cmdstan-2.30.1/stan/lib/stan_math/lib/tbb/tbbmalloc.def
scikit_stan/stan_files/cmdstan-2.30.1/stan/lib/stan_math/lib/tbb/condition_variable.o
scikit_stan/stan_files/cmdstan-2.30.1/stan/lib/stan_math/lib/tbb/cache_aligned_allocator.o
scikit_stan/stan_files/cmdstan-2.30.1/stan/lib/stan_math/lib/tbb/spin_rw_mutex.d
scikit_stan/stan_files/cmdstan-2.30.1/stan/lib/stan_math/lib/tbb/tbb_misc_ex.d
scikit_stan/stan_files/cmdstan-2.30.1/stan/lib/stan_math/lib/tbb/concurrent_queue_v2.o
scikit_stan/stan_files/cmdstan-2.30.1/stan/lib/stan_math/lib/tbb/proxy.d
scikit_stan/stan_files/cmdstan-2.30.1/stan/lib/stan_math/lib/tbb/scheduler.d
scikit_stan/stan_files/cmdstan-2.30.1/stan/lib/stan_math/lib/tbb/mutex.d
scikit_stan/stan_files/cmdstan-2.30.1/stan/lib/stan_math/lib/tbb/queuing_rw_mutex.o
scikit_stan/stan_files/cmdstan-2.30.1/stan/lib/stan_math/lib/tbb/tbb_function_replacement.d
scikit_stan/stan_files/cmdstan-2.30.1/stan/lib/stan_math/lib/tbb/libtbb.so
scikit_stan/stan_files/cmdstan-2.30.1/stan/lib/stan_math/lib/tbb/reader_writer_lock.o
scikit_stan/stan_files/cmdstan-2.30.1/stan/lib/stan_math/lib/tbb/scheduler.o
scikit_stan/stan_files/cmdstan-2.30.1/stan/lib/stan_math/lib/tbb/tbb_thread.d
