Metadata-Version: 2.1
Name: scikit_stan
Version: 0.1.1
Home-page: https://github.com/WardBrian/scikit-stan
Author: Alexey Izmailov, Brian Ward
License: BSD 3-Clause License
Provides-Extra: test
License-File: LICENSE
